ezbatch/__init__.py
ezbatch/_version.py
ezbatch/client.py
ezbatch/compute_environment.py
ezbatch/conf.py
ezbatch/defaults.py
ezbatch/job.py
ezbatch/job_definition.py
ezbatch/job_queue.py
ezbatch/logs.py
ezbatch/s3.py
ezbatch/workflow.py
ezbatch/interactive/__init__.py
ezbatch/interactive/manager.py
ezbatch/interactive/manager.tcss
ezbatch/preload_scripts/__init__.py
ezbatch/preload_scripts/preload.sh
ezbatch/scripts/__init__.py
ezbatch/scripts/cli.py
ezbatch-0.1.0.dist-info/licenses/LICENSE
ezbatch-0.1.0.dist-info/METADATA
ezbatch-0.1.0.dist-info/WHEEL
ezbatch-0.1.0.dist-info/entry_points.txt
ezbatch-0.1.0.dist-info/top_level.txt
ezbatch-0.1.0.dist-info/RECORD
