Metadata-Version: 2.4
Name: ezbatch
Version: 0.1.0
Summary: A Python Library for Simplified AWS Batch
Author-email: Andrew Van <vanandrew77@gmail.com>
License: MIT License
License-File: LICENSE
Requires-Dist: boto3
Requires-Dist: boto3-stubs[full]
Requires-Dist: dataclasses-json
Requires-Dist: pandas
Requires-Dist: random_word
Requires-Dist: tabulate
Requires-Dist: textual
Requires-Dist: toml
Provides-Extra: dev
Requires-Dist: pre-commit; extra == "dev"
Requires-Dist: pytest; extra == "dev"
Requires-Dist: textual-dev; extra == "dev"
Requires-Dist: sphinx; extra == "dev"
Requires-Dist: myst-parser; extra == "dev"
Requires-Dist: pydata-sphinx-theme; extra == "dev"
Dynamic: license-file
